LICENSE
MANIFEST.in
README.md
setup.py
docs/.DS_Store
docs/Makefile
docs/logs.log
docs/make.bat
docs/build/.DS_Store
docs/build/doctrees/environment.pickle
docs/build/doctrees/index.doctree
docs/build/html/.buildinfo
docs/build/html/genindex.html
docs/build/html/index.html
docs/build/html/objects.inv
docs/build/html/py-modindex.html
docs/build/html/search.html
docs/build/html/searchindex.js
docs/build/html/_sources/index.rst.txt
docs/build/html/_static/_sphinx_javascript_frameworks_compat.js
docs/build/html/_static/basic.css
docs/build/html/_static/doctools.js
docs/build/html/_static/documentation_options.js
docs/build/html/_static/file.png
docs/build/html/_static/jquery.js
docs/build/html/_static/language_data.js
docs/build/html/_static/minus.png
docs/build/html/_static/plus.png
docs/build/html/_static/pygments.css
docs/build/html/_static/searchtools.js
docs/build/html/_static/sphinx_highlight.js
docs/build/html/_static/css/badge_only.css
docs/build/html/_static/css/theme.css
docs/build/html/_static/css/fonts/Roboto-Slab-Bold.woff
docs/build/html/_static/css/fonts/Roboto-Slab-Bold.woff2
docs/build/html/_static/css/fonts/Roboto-Slab-Regular.woff
docs/build/html/_static/css/fonts/Roboto-Slab-Regular.woff2
docs/build/html/_static/css/fonts/fontawesome-webfont.eot
docs/build/html/_static/css/fonts/fontawesome-webfont.svg
docs/build/html/_static/css/fonts/fontawesome-webfont.ttf
docs/build/html/_static/css/fonts/fontawesome-webfont.woff
docs/build/html/_static/css/fonts/fontawesome-webfont.woff2
docs/build/html/_static/css/fonts/lato-bold-italic.woff
docs/build/html/_static/css/fonts/lato-bold-italic.woff2
docs/build/html/_static/css/fonts/lato-bold.woff
docs/build/html/_static/css/fonts/lato-bold.woff2
docs/build/html/_static/css/fonts/lato-normal-italic.woff
docs/build/html/_static/css/fonts/lato-normal-italic.woff2
docs/build/html/_static/css/fonts/lato-normal.woff
docs/build/html/_static/css/fonts/lato-normal.woff2
docs/build/html/_static/js/badge_only.js
scbk_mlops.egg-info/PKG-INFO
scbk_mlops.egg-info/SOURCES.txt
scbk_mlops.egg-info/dependency_links.txt
scbk_mlops.egg-info/requires.txt
scbk_mlops.egg-info/top_level.txt