Metadata-Version: 2.1
Name: scbk-mlops
Version: 0.3.3
Summary: Local version of MLOps intended for limited capabilities (no DB connection) under network segregation
Home-page: https://github.com/scbk-datascience/scbk-mlops
Author: Jong Hwa Lee, Jin Young Kim
Author-email: jonghwa.jh.lee@sc.com, jinyoung.jy.kim@sc.com
Classifier: Programming Language :: Python :: 3
Classifier: Operating System :: OS Independent
Requires-Python: >=3.10
License-File: LICENSE
